msur_crc/crc16.cpython-311-darwin.so
msur_crc-1.0.1.dist-info/METADATA
msur_crc-1.0.1.dist-info/WHEEL
msur_crc-1.0.1.dist-info/top_level.txt
msur_crc-1.0.1.dist-info/RECORD
