Metadata-Version: 2.1
Name: msur-crc
Version: 1.0.1
Home-page: https://github.com/msu-robotics/msur-crc
Author: Photon94
Author-email: 299792458.photon.94@gmail.com
License: MIT
Project-URL: Source, https://github.com/msu-robotics/msur-crc
Requires-Dist: importlib-metadata ; python_version >= "3.8"
